AUTHORS.md
LICENSE.txt
MANIFEST.in
README.md
pbs3.py
setup.py
pbs3.egg-info/PKG-INFO
pbs3.egg-info/SOURCES.txt
pbs3.egg-info/dependency_links.txt
pbs3.egg-info/top_level.txt