Metadata-Version: 1.0
Name: pbs3
Version: 3.0.2
Summary: pbs3 is a python package for launching external processes easily.
Home-page: http://github.com/xapple/pbs3/
Author: Lucas Sinclair
Author-email: lucas.sinclair@me.com
License: MIT
Platform: UNKNOWN
